sigma/validators/sigmahq/__init__.py
sigma/validators/sigmahq/author.py
sigma/validators/sigmahq/condition.py
sigma/validators/sigmahq/config.py
sigma/validators/sigmahq/correlation.py
sigma/validators/sigmahq/data/sigmahq_data.py
sigma/validators/sigmahq/date.py
sigma/validators/sigmahq/description.py
sigma/validators/sigmahq/detection.py
sigma/validators/sigmahq/falsepositive.py
sigma/validators/sigmahq/field.py
sigma/validators/sigmahq/fields.py
sigma/validators/sigmahq/filename.py
sigma/validators/sigmahq/level.py
sigma/validators/sigmahq/logsource.py
sigma/validators/sigmahq/references.py
sigma/validators/sigmahq/status.py
sigma/validators/sigmahq/tags.py
sigma/validators/sigmahq/title.py
pysigma_validators_sigmahq-0.20.1.dist-info/METADATA
pysigma_validators_sigmahq-0.20.1.dist-info/WHEEL
pysigma_validators_sigmahq-0.20.1.dist-info/licenses/LICENSE
pysigma_validators_sigmahq-0.20.1.dist-info/RECORD
