Metadata-Version: 2.4
Name: pySigma-validators-sigmahq
Version: 0.20.1
Summary: pySigma SigmaHQ validators
License-Expression: LGPL-2.1-only
License-File: LICENSE
Keywords: pySigma,SigmaHQ,validators
Author: François Hubaut
Author-email: frack113@users.noreply.github.com
Maintainer: François Hubaut
Maintainer-email: frack113@users.noreply.github.com
Requires-Python: >=3.10,<4.0
Classifier: Programming Language :: Python :: 3
Classifier: Programming Language :: Python :: 3.10
Classifier: Programming Language :: Python :: 3.11
Classifier: Programming Language :: Python :: 3.12
Classifier: Programming Language :: Python :: 3.13
Classifier: Programming Language :: Python :: 3.14
Requires-Dist: pysigma (>=1.0)
Requires-Dist: requests (>=2.32)
Project-URL: Repository, https://github.com/SigmaHQ/pySigma_validators_sigmaHQ
